calendar_api/__init__.py
calendar_api/calendar_api.py
python_google_calendar_api-0.5.dist-info/DESCRIPTION.rst
python_google_calendar_api-0.5.dist-info/METADATA
python_google_calendar_api-0.5.dist-info/RECORD
python_google_calendar_api-0.5.dist-info/WHEEL
python_google_calendar_api-0.5.dist-info/metadata.json
python_google_calendar_api-0.5.dist-info/top_level.txt
