Metadata-Version: 2.0
Name: python-google-calendar-api
Version: 0.5
Summary: A simple app to integrate Google calendar.
Home-page: https://bitbucket.org/kingmray/django-google-calendar
Author: Yash Nagar
Author-email: UNKNOWN
License: BSD License
Platform: UNKNOWN
Requires-Dist: google-api-python-client
Requires-Dist: pyOpenSSL
Requires-Dist: pytz
